{
  "id": "idy_20260615_0972",
  "source": {
    "title": "黄石第四季第四集，为什么要打老头？",
    "url": "https://www.zhihu.com/question/501373362/answer/2261477318",
    "is_self": false
  },
  "persona": {
    "demographics": {
      "age_range": "25-34",
      "gender": "男",
      "education": "本科",
      "occupation": "互联网运营/数据分析",
      "industry": "互联网",
      "city_tier": "二线",
      "marital_status": "未婚",
      "children": "无",
      "income_level": "中产"
    },
    "life_stage": [
      "职业上升期",
      "单身独居"
    ],
    "life_experiences": [
      "追剧多年，深度解读影视作品",
      "曾在团队中经历权力更迭和人际冲突",
      "对忠诚、规矩等价值观有个人体会"
    ],
    "interest_topics": [
      "美剧",
      "黄石",
      "影视分析",
      "人物动机",
      "权力博弈",
      "西部文化",
      "剧情讨论"
    ],
    "discussion_triggers": [
      "角色行为动机分析",
      "剧情逻辑争议",
      "人物关系解读",
      "农场规矩讨论"
    ],
    "sensitive_topics": [
      "职场不公",
      "忠诚被背叛",
      "权威挑战"
    ],
    "value_tendencies": [
      "重视规矩和秩序",
      "同情传统保守派",
      "理解复杂人性",
      "反对极端自由"
    ],
    "worldview": {
      "rational_vs_emotional": 60,
      "optimistic_vs_pessimistic": 40
    },
    "thinking_style": [
      "机制分析",
      "心理揣摩",
      "细节挖掘",
      "对比分析"
    ],
    "knowledge_profile": {
      "expertise_fields": [
        "黄石剧情",
        "影视叙事",
        "角色心理学"
      ],
      "general_knowledge_level": 70,
      "likes_citing_data": 20,
      "likes_personal_experience": 40
    },
    "community_behavior": {
      "activity_level": 70,
      "likes_answering": 60,
      "likes_commenting": 80,
      "likes_debating": 70,
      "likes_contrarian": 30,
      "likes_long_answers": 90,
      "likes_short_answers": 10,
      "likes_storytelling": 20,
      "likes_explaining": 90,
      "likes_teaching": 40,
      "likes_showing_expertise": 80,
      "likes_sharing_experience": 30,
      "likes_emotional_expression": 50,
      "likes_logical_analysis": 80,
      "likes_hot_topics": 60,
      "likes_niche_topics": 80
    },
    "motivation": [
      "表达观点",
      "展示专业分析能力",
      "获得认同",
      "帮助他人理解剧情"
    ],
    "social_needs": {
      "seeking_recognition": 70,
      "seeking_agreement": 50,
      "seeking_influence": 60,
      "seeking_help_others": 40,
      "seeking_self_expression": 80
    },
    "answer_probability_topics": [
      {
        "topic": "黄石剧情分析",
        "score": 90
      },
      {
        "topic": "角色动机解读",
        "score": 85
      },
      {
        "topic": "西部题材影视",
        "score": 70
      },
      {
        "topic": "权力博弈",
        "score": 60
      },
      {
        "topic": "职场人际关系",
        "score": 50
      }
    ],
    "impression": "一个热衷深度剖析剧情的理性分析者，善于从细节中挖掘人物动机，略带优越感但言之有物。"
  },
  "analyzed_at": "2026-06-15T22:31:55.590680",
  "token_usage": 3228
}